console_quiet/__init__.py
console_quiet-1.0.1.dist-info/LICENSE
console_quiet-1.0.1.dist-info/WHEEL
console_quiet-1.0.1.dist-info/METADATA
console_quiet-1.0.1.dist-info/RECORD
