Metadata-Version: 2.1
Name: console_quiet
Version: 1.0.1
Summary: Provides a context manager for doing a "deep suppression" of stdout and stderr.
Author-email: Leon Dionne <ldionne@dridesign.sh.cn>
Classifier: License :: OSI Approved :: GNU General Public License v3 or later (GPLv3+)
Classifier: Programming Language :: Python
Classifier: Programming Language :: Python :: 3.10
Classifier: Topic :: Terminals
Classifier: Topic :: Utilities
Project-URL: Home, https://github.com/Zen-Master-SoSo/console_quiet
